<?xml version="1.0" encoding="utf-8"?>
<executable>

  <category>Filtering</category>
  <title>Merge (TubeTK)</title>
  <description>Merge the second image into the space of the first</description>
  <version>0.1.0.$Revision: 2104 $(alpha)</version>
  <documentation-url>http://public.kitware.com/Wiki/TubeTK</documentation-url>
  <license>Apache 2.0</license>
  <contributor>Stephen R. Aylward, Kitware</contributor>
  <acknowledgements>This work is part of the TubeTK project at Kitware.</acknowledgements>

  <parameters>
    <label>IO</label>
    <description>Input/output parameters</description>
    <image>
      <name>inputVolume1</name>
      <label>Input Volume 1</label>
      <channel>input</channel>
      <index>0</index>
      <description>Input volume 1</description>
    </image>
    <image multiple="true">
      <name>inputVolume2</name>
      <label>Input Volume 2</label>
      <description>Input volume 2</description>
      <longflag>mergeVolumes</longflag>
      <flag>m</flag>
    </image>
    <image>
      <name>outputVolume</name>
      <label>Output Volume</label>
      <channel>output</channel>
      <index>1</index>
      <description>Output Volume</description>
    </image>
  </parameters>

  <parameters>
    <label>Merge options</label>
    <boolean>
      <name>average</name>
      <label>Average values</label>
      <description>Average values when overlap occurs</description>
      <longflag>average</longflag>
      <flag>a</flag>
      <default>false</default>
    </boolean>
    <boolean>
      <name>weighted</name>
      <label>Distance weighted</label>
      <description>Weighted average based on depth of overlap</description>
      <longflag>weighted</longflag>
      <flag>w</flag>
      <default>false</default>
    </boolean>
    <double>
      <name>background</name>
      <label>Background intensity</label>
      <description>Value to assign to pixels in the output image that don't intersect an input image</description>
      <longflag>background</longflag>
      <flag>k</flag>
      <default>0</default>
    </double>
  </parameters>
  <parameters>
    <label>Registration options</label>
    <integer>
      <name>iterations</name>
      <label>Registration iterations</label>
      <description>Number of iterations (0=no registration)</description>
      <longflag>iterations</longflag>
      <flag>i</flag>
      <default>300</default>
    </integer>
    <integer-vector>
      <name>boundary</name>
      <label>Additional boundary pixels</label>
      <description>Pixels to be added around the second image as padding (account for registration movement)</description>
      <longflag>boundary</longflag>
      <flag>b</flag>
      <default></default>
    </integer-vector>
    <float>
      <name>expectedOffset</name>
      <label>Expected misalignment (offset)</label>
      <description>Expected initial mis-registration between the images</description>
      <longflag>expectedOffset</longflag>
      <flag>o</flag>
      <default>20</default>
    </float>
    <float>
      <name>expectedRotation</name>
      <label>Expected misalignment (rotation)</label>
      <description>Expected initial mis-registration between the images</description>
      <longflag>expectedRotation</longflag>
      <flag>r</flag>
      <default>0.001</default>
    </float>
    <float>
      <name>samplingRatio</name>
      <label>Sampling ratio</label>
      <description>Portion of pixels to use for registration</description>
      <longflag>samplingRatio</longflag>
      <flag>s</flag>
      <default>0.01</default>
    </float>
    <string>
      <name>saveTransform</name>
      <label>Save transform</label>
      <description>Filename to save the transform to</description>
      <longflag>saveTransform</longflag>
      <flag>S</flag>
      <default></default>
    </string>
  </parameters>

</executable>
